pysmspp/__init__.py
pysmspp/block.py
pysmspp/components.py
pysmspp/helpers.py
pysmspp/smspp_tools.py
pysmspp/data/components.csv
pysmspp/data/blocks/AbstractPath.csv
pysmspp/data/blocks/BatteryUnitBlock.csv
pysmspp/data/blocks/DesignNetworkBlock.csv
pysmspp/data/blocks/DiscreteScenarioSet.csv
pysmspp/data/blocks/HydroUnitBlock.csv
pysmspp/data/blocks/IntermittentUnitBlock.csv
pysmspp/data/blocks/InvestmentBlock.csv
pysmspp/data/blocks/SlackUnitBlock.csv
pysmspp/data/blocks/StochasticBlock.csv
pysmspp/data/blocks/ThermalUnitBlock.csv
pysmspp/data/blocks/TwoStageStochasticBlock.csv
pysmspp/data/blocks/UCBlock.csv
pysmspp/data/blocks/UCBlockSolution.csv
pysmspp/data/blocks/UnitBlockSolution.csv
pysmspp/data/configs/InvestmentBlock/BSPar.txt
pysmspp/data/configs/InvestmentBlock/uc_solverconfig.txt
pysmspp/data/configs/InvestmentBlock/uc_solverconfig_grb.txt
pysmspp/data/configs/UCBlock/uc_solverconfig.txt
pysmspp/data/configs/UCBlock/uc_solverconfig_grb.txt
pysmspp-0.0.2.dist-info/licenses/LICENSE
pysmspp-0.0.2.dist-info/METADATA
pysmspp-0.0.2.dist-info/WHEEL
pysmspp-0.0.2.dist-info/top_level.txt
pysmspp-0.0.2.dist-info/RECORD
