Metadata-Version: 2.4
Name: pysmspp
Version: 0.0.2
Summary: Basic interface to interact with SMS++
Author-email: Unipi developers <davide.fioriti@unipi.it>
Project-URL: Homepage, https://github.com/SPSUnipi/pySMSpp
Project-URL: Issues, https://github.com/SPSUnipi/pySMSpp/issues
Classifier: Programming Language :: Python :: 3.12
Classifier: Programming Language :: Python :: 3.13
Classifier: License :: OSI Approved :: GNU General Public License v3 or later (GPLv3+)
Classifier: Operating System :: OS Independent
Requires-Python: >=3.12
License-File: LICENSE
Requires-Dist: numpy
Requires-Dist: pandas>=0.24
Requires-Dist: netcdf4
Requires-Dist: pathlib
Requires-Dist: psutil
Provides-Extra: dev
Requires-Dist: pytest; extra == "dev"
Requires-Dist: coverage; extra == "dev"
Requires-Dist: pre-commit; extra == "dev"
Requires-Dist: ncompare; extra == "dev"
Requires-Dist: mypy; extra == "dev"
Requires-Dist: h5py<3.15; extra == "dev"
Provides-Extra: docs
Requires-Dist: numpydoc; extra == "docs"
Requires-Dist: sphinx; extra == "docs"
Requires-Dist: sphinx-book-theme; extra == "docs"
Requires-Dist: sphinx-rtd-theme; extra == "docs"
Requires-Dist: pydata-sphinx-theme; extra == "docs"
Requires-Dist: sphinx-reredirects; extra == "docs"
Requires-Dist: nbsphinx; extra == "docs"
Requires-Dist: nbsphinx-link; extra == "docs"
Requires-Dist: scikit-learn; extra == "docs"
Requires-Dist: ipython; extra == "docs"
Requires-Dist: ipykernel; extra == "docs"
Dynamic: license-file
